service_checker/__init__.py
service_checker-0.1.0.dev4.dist-info/LICENSE
service_checker-0.1.0.dev4.dist-info/METADATA
service_checker-0.1.0.dev4.dist-info/WHEEL
service_checker-0.1.0.dev4.dist-info/entry_points.txt
service_checker-0.1.0.dev4.dist-info/top_level.txt
service_checker-0.1.0.dev4.dist-info/RECORD
