Metadata-Version: 2.1
Name: service-checker
Version: 0.1.0.dev4
Summary: Check services with commands and trigger commands
Home-page: https://github.com/adesso-mobile/service_checker
Author: adesso mobile solutions GmbH
Author-email: it-operations@adesso-mobile.de
License: UNKNOWN
Project-URL: Bug Tracker, https://github.com/adesso-mobile/service_checker/issues
Platform: UNKNOWN
Classifier: Programming Language :: Python :: 3
Classifier: License :: OSI Approved :: MIT License
Classifier: Operating System :: OS Independent
Requires-Python: >=3.6
Requires-Dist: pyyaml
Requires-Dist: prometheus-client
